tf_image_processing/__init__.py
tf_image_processing/sample_img_transfer-hist.py
tf_image_processing/processing/__init__.py
tf_image_processing/processing/combination.py
tf_image_processing/processing/transformation.py
tf_image_processing/utils/__init__.py
tf_image_processing/utils/io.py
tf_image_processing/utils/plot.py
tf_image_processing-0.0.1.dist-info/METADATA
tf_image_processing-0.0.1.dist-info/WHEEL
tf_image_processing-0.0.1.dist-info/top_level.txt
tf_image_processing-0.0.1.dist-info/RECORD
