Metadata-Version: 2.1
Name: tf-image-processing
Version: 0.0.1
Summary: modules for transforming images and its colors through a histogram reference
Home-page: https://github.com/EngThiagoFerrari/image-processing-package.git
Author: Thiago Ferrari
Author-email: engthiagoferrari@gmail.com
Requires-Python: >=3.9.0
